Authors.conf
CHANGES
COPYING
MANIFEST.in
README.md
TODO
setup.py
dkimpy_milter/__init__.py
dkimpy_milter/__main__.py
dkimpy_milter/config.py
dkimpy_milter/dnsplug.py
dkimpy_milter/util.py
dkimpy_milter.egg-info/PKG-INFO
dkimpy_milter.egg-info/SOURCES.txt
dkimpy_milter.egg-info/dependency_links.txt
dkimpy_milter.egg-info/entry_points.txt
dkimpy_milter.egg-info/not-zip-safe
dkimpy_milter.egg-info/requires.txt
dkimpy_milter.egg-info/top_level.txt
etc/dkimpy-milter.conf
etc/dkimpy-milter.conf.in
man/dkimpy-milter.8
man/dkimpy-milter.conf.5
man/dkimpy-milter.conf.5.in
system/dkimpy-milter
system/dkimpy-milter.in
system/dkimpy-milter.openrc
system/dkimpy-milter.openrc.in
system/dkimpy-milter.service
system/dkimpy-milter.service.in