Metadata-Version: 2.1
Name: dkimpy-milter
Version: 1.2.3
Summary: Domain Keys Identified Mail (DKIM) signing/verifying milter for Postfix/Sendmail.
Home-page: https://launchpad.net/dkimpy-milter
Author: Scott Kitterman
Author-email: scott@kitterman.com
License: UNKNOWN
Download-URL: https://pypi.python.org/pypi/dkimpy-milter
Platform: UNKNOWN
Classifier: Development Status :: 5 - Production/Stable
Classifier: Environment :: No Input/Output (Daemon)
Classifier: Intended Audience :: System Administrators
Classifier: License :: OSI Approved :: GNU General Public License (GPL)
Classifier: Natural Language :: English
Classifier: Operating System :: POSIX
Classifier: Programming Language :: Python :: 3 :: Only
Classifier: Topic :: Communications :: Email :: Mail Transport Agents
Classifier: Topic :: Communications :: Email :: Filters
Classifier: Topic :: Security
